odoo10_addon_l10n_nl_xaf_auditfile_export-10.0.1.2.1-py3.8-nspkg.pth
odoo/addons/l10n_nl_xaf_auditfile_export/README.rst
odoo/addons/l10n_nl_xaf_auditfile_export/__init__.py
odoo/addons/l10n_nl_xaf_auditfile_export/__manifest__.py
odoo/addons/l10n_nl_xaf_auditfile_export/data/XmlAuditfileFinancieel3.2.xsd
odoo/addons/l10n_nl_xaf_auditfile_export/i18n/l10n_nl_xaf_auditfile_export.pot
odoo/addons/l10n_nl_xaf_auditfile_export/i18n/nl.po
odoo/addons/l10n_nl_xaf_auditfile_export/i18n/nl_NL.po
odoo/addons/l10n_nl_xaf_auditfile_export/models/__init__.py
odoo/addons/l10n_nl_xaf_auditfile_export/models/ir_qweb.py
odoo/addons/l10n_nl_xaf_auditfile_export/models/xaf_auditfile_export.py
odoo/addons/l10n_nl_xaf_auditfile_export/security/ir.model.access.csv
odoo/addons/l10n_nl_xaf_auditfile_export/static/description/icon.png
odoo/addons/l10n_nl_xaf_auditfile_export/tests/__init__.py
odoo/addons/l10n_nl_xaf_auditfile_export/tests/test_l10n_nl_xaf_auditfile_export.py
odoo/addons/l10n_nl_xaf_auditfile_export/views/menu.xml
odoo/addons/l10n_nl_xaf_auditfile_export/views/templates.xml
odoo/addons/l10n_nl_xaf_auditfile_export/views/xaf_auditfile_export.xml
odoo10_addon_l10n_nl_xaf_auditfile_export-10.0.1.2.1.dist-info/METADATA
odoo10_addon_l10n_nl_xaf_auditfile_export-10.0.1.2.1.dist-info/WHEEL
odoo10_addon_l10n_nl_xaf_auditfile_export-10.0.1.2.1.dist-info/namespace_packages.txt
odoo10_addon_l10n_nl_xaf_auditfile_export-10.0.1.2.1.dist-info/top_level.txt
odoo10_addon_l10n_nl_xaf_auditfile_export-10.0.1.2.1.dist-info/RECORD
